{
  "template": "https://github.com/vshn/appcat-cookiecutter",
  "commit": "7b2e701de40e4f54a12e08fdfb7f12431c9742ce",
  "checkout": null,
  "context": {
    "cookiecutter": {
      "app_name": "provider-exoscale",
      "component_repo": "vshn/component-appcat",
      "push_upbound": true,
      "push_package": true,
      "push_image": false,
      "_copy_without_render": [
        ".github/workflows/cruft-update.yml",
        ".github/changelog-configuration.json"
      ],
      "_template": "https://github.com/vshn/appcat-cookiecutter"
    }
  },
  "directory": null
}
